{
  "width": 5761,
  "height": 4039,
  "bounds": {
    "node__1": {
      "x": 357.0,
      "y": 339.0,
      "width": 304.0,
      "height": 76.0,
      "cx": 509.0,
      "cy": 377.0
    },
    "node__1-a": {
      "x": 421.0,
      "y": 516.32,
      "width": 240.0,
      "height": 76.0,
      "cx": 541.0,
      "cy": 554.32
    },
    "node__1-a-1": {
      "x": 799.74,
      "y": 462.0,
      "width": 218.0,
      "height": 214.85,
      "cx": 908.74,
      "cy": 569.43
    },
    "node__1-a-2": {
      "x": 1081.74,
      "y": 465.1,
      "width": 189.0,
      "height": 214.69,
      "cx": 1176.24,
      "cy": 572.44
    },
    "node__1-b": {
      "x": 357.0,
      "y": 797.32,
      "width": 304.0,
      "height": 76.0,
      "cx": 509.0,
      "cy": 835.32
    },
    "node__1-b-1": {
      "x": 799.73,
      "y": 745.99,
      "width": 207.0,
      "height": 211.6,
      "cx": 903.23,
      "cy": 851.79
    },
    "node__1-b-2": {
      "x": 1070.67,
      "y": 745.92,
      "width": 228.0,
      "height": 193.52,
      "cx": 1184.67,
      "cy": 842.68
    },
    "node__1-b-3": {
      "x": 1352.74,
      "y": 744.12,
      "width": 249.0,
      "height": 214.52,
      "cx": 1477.24,
      "cy": 851.38
    },
    "node__1-c": {
      "x": 165.0,
      "y": 1095.32,
      "width": 496.0,
      "height": 76.0,
      "cx": 413.0,
      "cy": 1133.32
    },
    "node__1-c-1": {
      "x": 799.74,
      "y": 1027.14,
      "width": 179.0,
      "height": 214.85,
      "cx": 889.24,
      "cy": 1134.57
    },
    "node__1-c-2": {
      "x": 1047.79,
      "y": 1026.8,
      "width": 275.0,
      "height": 229.52,
      "cx": 1185.29,
      "cy": 1141.56
    },
    "node__1-c-3": {
      "x": 1356.74,
      "y": 1026.9,
      "width": 246.0,
      "height": 214.52,
      "cx": 1479.74,
      "cy": 1134.16
    },
    "node__1-c-4": {
      "x": 1654.74,
      "y": 1027.05,
      "width": 204.0,
      "height": 214.52,
      "cx": 1756.74,
      "cy": 1134.31
    },
    "node__1-c-5": {
      "x": 1913.74,
      "y": 1027.14,
      "width": 179.0,
      "height": 214.52,
      "cx": 2003.24,
      "cy": 1134.4
    },
    "node__2": {
      "x": 303.0,
      "y": 1401.0,
      "width": 368.0,
      "height": 76.0,
      "cx": 487.0,
      "cy": 1439.0
    },
    "node__2-a": {
      "x": 303.0,
      "y": 1666.46,
      "width": 304.0,
      "height": 76.0,
      "cx": 455.0,
      "cy": 1704.46
    },
    "node__2-a-1": {
      "x": 745.74,
      "y": 1598.6,
      "width": 220.0,
      "height": 214.52,
      "cx": 855.74,
      "cy": 1705.86
    },
    "node__2-a-2": {
      "x": 1043.92,
      "y": 1597.0,
      "width": 156.0,
      "height": 265.85,
      "cx": 1121.92,
      "cy": 1729.93
    },
    "node__2-b": {
      "x": 303.0,
      "y": 1987.46,
      "width": 304.0,
      "height": 76.0,
      "cx": 455.0,
      "cy": 2025.46
    },
    "node__2-b-1": {
      "x": 745.74,
      "y": 1918.21,
      "width": 275.0,
      "height": 214.52,
      "cx": 883.24,
      "cy": 2025.47
    },
    "node__2-b-2": {
      "x": 1097.74,
      "y": 1918.51,
      "width": 189.0,
      "height": 214.52,
      "cx": 1192.24,
      "cy": 2025.77
    },
    "node__2-b-3": {
      "x": 1390.74,
      "y": 1918.65,
      "width": 150.0,
      "height": 214.52,
      "cx": 1465.74,
      "cy": 2025.91
    },
    "node__2-b-4": {
      "x": 1635.74,
      "y": 1917.17,
      "width": 204.0,
      "height": 214.52,
      "cx": 1737.74,
      "cy": 2024.43
    },
    "node__2-c": {
      "x": 303.0,
      "y": 2306.46,
      "width": 304.0,
      "height": 76.0,
      "cx": 455.0,
      "cy": 2344.46
    },
    "node__2-c-1": {
      "x": 745.74,
      "y": 2237.65,
      "width": 150.0,
      "height": 214.52,
      "cx": 820.74,
      "cy": 2344.91
    },
    "node__2-c-2": {
      "x": 953.74,
      "y": 2237.58,
      "width": 169.0,
      "height": 214.52,
      "cx": 1038.24,
      "cy": 2344.84
    },
    "node__2-c-3": {
      "x": 1180.74,
      "y": 2241.14,
      "width": 218.0,
      "height": 214.52,
      "cx": 1289.74,
      "cy": 2348.4
    },
    "node__2-c-4": {
      "x": 1456.84,
      "y": 2236.98,
      "width": 342.0,
      "height": 244.52,
      "cx": 1627.84,
      "cy": 2359.24
    },
    "node__3": {
      "x": 2660.0,
      "y": 339.0,
      "width": 304.0,
      "height": 76.0,
      "cx": 2812.0,
      "cy": 377.0
    },
    "node__3-a": {
      "x": 2661.0,
      "y": 534.11,
      "width": 304.0,
      "height": 140.0,
      "cx": 2813.0,
      "cy": 604.11
    },
    "node__3-a-1": {
      "x": 3103.95,
      "y": 465.0,
      "width": 236.0,
      "height": 274.52,
      "cx": 3221.95,
      "cy": 602.26
    },
    "node__3-a-2": {
      "x": 3401.64,
      "y": 465.3,
      "width": 150.0,
      "height": 184.52,
      "cx": 3476.64,
      "cy": 557.56
    },
    "node__3-a-3": {
      "x": 3612.85,
      "y": 465.06,
      "width": 218.0,
      "height": 245.02,
      "cx": 3721.85,
      "cy": 587.57
    },
    "node__3-b": {
      "x": 2788.76,
      "y": 866.79,
      "width": 176.0,
      "height": 76.0,
      "cx": 2876.76,
      "cy": 904.79
    },
    "node__3-b-1": {
      "x": 3103.5,
      "y": 829.6,
      "width": 256.0,
      "height": 214.52,
      "cx": 3231.5,
      "cy": 936.86
    },
    "node__3-b-2": {
      "x": 3448.0,
      "y": 829.34,
      "width": 332.0,
      "height": 359.52,
      "cx": 3614.0,
      "cy": 1009.1
    },
    "node__3-c": {
      "x": 2788.27,
      "y": 1345.79,
      "width": 176.0,
      "height": 76.0,
      "cx": 2876.27,
      "cy": 1383.79
    },
    "node__3-c-1": {
      "x": 3103.14,
      "y": 1308.38,
      "width": 321.0,
      "height": 280.69,
      "cx": 3263.64,
      "cy": 1448.72
    },
    "node__3-c-2": {
      "x": 3487.27,
      "y": 1308.34,
      "width": 266.0,
      "height": 220.52,
      "cx": 3620.27,
      "cy": 1418.6
    },
    "node__3-d": {
      "x": 2724.27,
      "y": 1787.79,
      "width": 240.0,
      "height": 76.0,
      "cx": 2844.27,
      "cy": 1825.79
    },
    "node__3-d-1": {
      "x": 3103.19,
      "y": 1748.94,
      "width": 332.0,
      "height": 265.52,
      "cx": 3269.19,
      "cy": 1881.7
    },
    "node__4": {
      "x": 2660.0,
      "y": 2171.0,
      "width": 176.0,
      "height": 76.0,
      "cx": 2748.0,
      "cy": 2209.0
    },
    "node__5": {
      "x": 2660.0,
      "y": 2814.0,
      "width": 176.0,
      "height": 76.0,
      "cx": 2748.0,
      "cy": 2852.0
    },
    "node__6": {
      "x": 2660.0,
      "y": 3344.0,
      "width": 176.0,
      "height": 76.0,
      "cx": 2748.0,
      "cy": 3382.0
    }
  }
}
